<?xml version="1.0" encoding="UTF-8"?>
<GenRun Id="synth_1" LaunchPart="xc7z020clg484-1" LaunchTime="1652041567">
  <File Type="PA-TCL" Name="sistema_digital.tcl"/>
  <File Type="RDS-PROPCONSTRS" Name="sistema_digital_drc_synth.rpt"/>
  <File Type="REPORTS-TCL" Name="sistema_digital_reports.tcl"/>
  <File Type="RDS-RDS" Name="sistema_digital.vds"/>
  <File Type="RDS-UTIL" Name="sistema_digital_utilization_synth.rpt"/>
  <File Type="RDS-UTIL-PB" Name="sistema_digital_utilization_synth.pb"/>
  <File Type="RDS-DCP" Name="sistema_digital.dcp"/>
  <File Type="VDS-TIMINGSUMMARY" Name="sistema_digital_timing_summary_synth.rpt"/>
  <File Type="VDS-TIMING-PB" Name="sistema_digital_timing_summary_synth.pb"/>
  <FileSet Name="sources" Type="DesignSrcs" RelSrcDir="$PSRCDIR/sources_1">
    <Filter Type="Srcs"/>
    <File Path="$PSRCDIR/sources_1/imports/lab1/lab1_parteF_BCD/lab1_parteF_BCD.srcs/sources_1/new/BCD_counter.vhd">
      <FileInfo>
        <Attr Name="ImportPath" Val="$PPRDIR/../lab1_parteF_BCD/lab1_parteF_BCD.srcs/sources_1/new/BCD_counter.vhd"/>
        <Attr Name="ImportTime" Val="1651845994"/>
        <Attr Name="UsedIn" Val="synthesis"/>
        <Attr Name="UsedIn" Val="simulation"/>
      </FileInfo>
    </File>
    <File Path="$PSRCDIR/sources_1/new/FF_D.vhd">
      <FileInfo>
        <Attr Name="UsedIn" Val="synthesis"/>
        <Attr Name="UsedIn" Val="simulation"/>
      </FileInfo>
    </File>
    <File Path="$PSRCDIR/sources_1/new/LSFR_4bits.vhd">
      <FileInfo>
        <Attr Name="UsedIn" Val="synthesis"/>
        <Attr Name="UsedIn" Val="simulation"/>
      </FileInfo>
    </File>
    <File Path="$PSRCDIR/sources_1/imports/lab1/lab1_parteC/lab1_parteC.srcs/sources_1/new/PowerOnReset.vhd">
      <FileInfo>
        <Attr Name="ImportPath" Val="$PPRDIR/../lab1_parteC/lab1_parteC.srcs/sources_1/new/PowerOnReset.vhd"/>
        <Attr Name="ImportTime" Val="1651201669"/>
        <Attr Name="UsedIn" Val="synthesis"/>
        <Attr Name="UsedIn" Val="simulation"/>
      </FileInfo>
    </File>
    <File Path="$PSRCDIR/sources_1/new/counter_28bits.vhd">
      <FileInfo>
        <Attr Name="UsedIn" Val="synthesis"/>
        <Attr Name="UsedIn" Val="simulation"/>
      </FileInfo>
    </File>
    <File Path="$PSRCDIR/sources_1/imports/lab1/lab1_parteE_counter/lab1_parteE_counter.srcs/sources_1/new/counter_Nbits.vhd">
      <FileInfo>
        <Attr Name="ImportPath" Val="$PPRDIR/../lab1_parteE_counter/lab1_parteE_counter.srcs/sources_1/new/counter_Nbits.vhd"/>
        <Attr Name="ImportTime" Val="1651791825"/>
        <Attr Name="UsedIn" Val="synthesis"/>
        <Attr Name="UsedIn" Val="simulation"/>
      </FileInfo>
    </File>
    <File Path="$PSRCDIR/sources_1/imports/lab1/lab1_parteE/lab1_parteE.srcs/sources_1/new/divisor_frecuencia.vhd">
      <FileInfo>
        <Attr Name="ImportPath" Val="$PPRDIR/../lab1_parteE/lab1_parteE.srcs/sources_1/new/divisor_frecuencia.vhd"/>
        <Attr Name="ImportTime" Val="1651793015"/>
        <Attr Name="UsedIn" Val="synthesis"/>
        <Attr Name="UsedIn" Val="simulation"/>
      </FileInfo>
    </File>
    <File Path="$PSRCDIR/sources_1/new/synchronizer.vhd">
      <FileInfo>
        <Attr Name="UsedIn" Val="synthesis"/>
        <Attr Name="UsedIn" Val="simulation"/>
      </FileInfo>
    </File>
    <File Path="$PSRCDIR/sources_1/new/sistema_digital.vhd">
      <FileInfo>
        <Attr Name="UsedIn" Val="synthesis"/>
        <Attr Name="UsedIn" Val="simulation"/>
      </FileInfo>
    </File>
    <Config>
      <Option Name="DesignMode" Val="RTL"/>
      <Option Name="TopModule" Val="sistema_digital"/>
      <Option Name="TopAutoSet" Val="TRUE"/>
    </Config>
  </FileSet>
  <FileSet Name="constrs_in" Type="Constrs" RelSrcDir="$PSRCDIR/constrs_1">
    <Filter Type="Constrs"/>
    <Config>
      <Option Name="ConstrsType" Val="XDC"/>
    </Config>
  </FileSet>
  <FileSet Name="utils" Type="Utils" RelSrcDir="$PSRCDIR/utils_1">
    <Filter Type="Utils"/>
    <Config>
      <Option Name="TopAutoSet" Val="TRUE"/>
    </Config>
  </FileSet>
  <Strategy Version="1" Minor="2">
    <StratHandle Name="Vivado Synthesis Defaults" Flow="Vivado Synthesis 2019"/>
    <Step Id="synth_design"/>
  </Strategy>
</GenRun>
